Workbook

Sheet Calendar
A1: NextGen Fusion — 100-day blog calendar
A2: Start date (edit): | C2: 46304 | E2: Yellow cell = change the start date and every publish date shifts. Edit Status as you go.
A4: Day | B4: Publish date | C4: Title | D4: Slug | E4: Category | F4: Primary keyword | G4: Service it leads to | H4: Read time (min) | I4: Status
A5: 1 | B5: =$C$2+A5-1 -> 46304 | C5: Why is my website not showing on Google? 10 checks before you panic | D5: /blog/website-not-showing-on-google | E5: SEO & AI search | F5: website not showing on google | G5: SEO & AI visibility | H5: 6 | I5: Planned
A6: 2 | B6: =$C$2+A6-1 -> 46305 | C6: Why is my Shopify store getting visitors but no sales? A conversion audit you can run today | D6: /blog/shopify-visitors-no-sales | E6: Shopify & e-commerce | F6: shopify visitors but no sales | G6: Shopify / e-commerce build & CRO | H6: 6 | I6: Planned
A7: 3 | B7: =$C$2+A7-1 -> 46306 | C7: How much does a business website cost in 2026? What you actually pay for, from template to custom build | D7: /blog/website-cost-2026 | E7: Cost & planning | F7: website development cost 2026 | G7: Website development | H7: 6 | I7: Planned
A8: 4 | B8: =$C$2+A8-1 -> 46307 | C8: Why is my website getting traffic but no enquiries? 9 reasons visitors leave without contacting you | D8: /blog/traffic-but-no-leads | E8: Website problems & redesign | F8: website traffic but no leads | G8: Website redesign | H8: 6 | I8: Planned
A9: 5 | B9: =$C$2+A9-1 -> 46308 | C9: Does your business need an AI chatbot? What it can and can't do in 2026 | D9: /blog/does-my-business-need-an-ai-chatbot | E9: AI & automation | F9: ai chatbot for small business | G9: AI chatbots, agents & automation | H9: 5 | I9: Planned
A10: 6 | B10: =$C$2+A10-1 -> 46309 | C10: Why is my WordPress site so slow? A step-by-step speed fix guide | D10: /blog/slow-wordpress-site | E10: WordPress & WooCommerce | F10: wordpress site slow | G10: WordPress / WooCommerce | H10: 6 | I10: Planned
A11: 7 | B11: =$C$2+A11-1 -> 46310 | C11: What is UX design, and why does it affect revenue? Explained for business owners | D11: /blog/ux-design-for-business-owners | E11: UI/UX & conversion | F11: what is ux design | G11: UI/UX design | H11: 5 | I11: Planned
A12: 8 | B12: =$C$2+A12-1 -> 46311 | C12: Off-the-shelf vs custom software: when building your own actually makes sense | D12: /blog/off-the-shelf-vs-custom-software | E12: Custom software & SaaS | F12: custom software vs off the shelf | G12: Custom software / SaaS development | H12: 5 | I12: Planned
A13: 9 | B13: =$C$2+A13-1 -> 46312 | C13: Is my website secure? A 15-point security checklist for business websites | D13: /blog/website-security-checklist | E13: Security, speed & maintenance | F13: website security checklist | G13: Maintenance, hosting & security | H13: 5 | I13: Planned
A14: 10 | B14: =$C$2+A14-1 -> 46313 | C14: How to hire a web developer without getting burned: questions to ask first | D14: /blog/how-to-hire-a-web-developer | E14: Hiring a developer | F14: how to hire a web developer | G14: Agency / consultation | H14: 5 | I14: Planned
A15: 11 | B15: =$C$2+A15-1 -> 46314 | C15: Does your business need a mobile app, or will a website do? | D15: /blog/app-or-website | E15: Mobile apps | F15: do i need an app or website | G15: Mobile app development | H15: 5 | I15: Planned
A16: 12 | B16: =$C$2+A16-1 -> 46315 | C16: Google traffic dropped but rankings didn't: how AI Overviews are changing clicks in 2026 | D16: /blog/ai-overviews-traffic-drop | E16: SEO & AI search | F16: google traffic dropped ai overviews | G16: SEO & AI visibility | H16: 6 | I16: Planned
... A104: 100 | B104: =$C$2+A104-1 -> 46403 | C104: Connecting your website, CRM and email with Make.com or n8n: a beginner's automation guide | D104: /blog/make-n8n-automation-guide | E104: AI & automation | F104: make.com n8n automation guide | G104: AI chatbots, agents & automation | H104: 5 | I104: Planned

Sheet By category
A1: Posts per category
A3: Category | B3: Posts
A4: SEO & AI search | B4: =COUNTIF(Calendar!$E$5:$E$104,A4) -> 10
A5: Shopify & e-commerce | B5: =COUNTIF(Calendar!$E$5:$E$104,A5) -> 10
A6: Cost & planning | B6: =COUNTIF(Calendar!$E$5:$E$104,A6) -> 9
A7: Website problems & redesign | B7: =COUNTIF(Calendar!$E$5:$E$104,A7) -> 9
A8: AI & automation | B8: =COUNTIF(Calendar!$E$5:$E$104,A8) -> 10
A9: WordPress & WooCommerce | B9: =COUNTIF(Calendar!$E$5:$E$104,A9) -> 9
A10: UI/UX & conversion | B10: =COUNTIF(Calendar!$E$5:$E$104,A10) -> 9
A11: Custom software & SaaS | B11: =COUNTIF(Calendar!$E$5:$E$104,A11) -> 9
A12: Security, speed & maintenance | B12: =COUNTIF(Calendar!$E$5:$E$104,A12) -> 9
A13: Hiring a developer | B13: =COUNTIF(Calendar!$E$5:$E$104,A13) -> 8
A14: Mobile apps | B14: =COUNTIF(Calendar!$E$5:$E$104,A14) -> 8
A15: Total | B15: =SUM(B4:B14) -> 100
